framedisplay/__init__.py
framedisplay/__version__.py
framedisplay/display.py
framedisplay/js/framedisplay.js
framedisplay/js/framedisplay.min.js
framedisplay/js/src/main.js
framedisplay/js/src/styles.css
framedisplay/js/src/version.js
framedisplay/tests/__init__.py
framedisplay/tests/conftest.py
framedisplay/tests/test_display.py
framedisplay/tests/utils.py
framedisplay-1.2.1.dist-info/licenses/LICENSE
framedisplay-1.2.1.dist-info/METADATA
framedisplay-1.2.1.dist-info/WHEEL
framedisplay-1.2.1.dist-info/top_level.txt
framedisplay-1.2.1.dist-info/RECORD
