Metadata-Version: 2.4
Name: framedisplay
Version: 1.2.1
Summary: Enhanced DataFrame Display
Home-page: https://github.com/nsarang/framedisplay
Author: Nima Sarang
Author-email: contact@nimasarang.com
Project-URL: Homepage, https://github.com/nsarang/framedisplay
Project-URL: Issues, https://github.com/nsarang/framedisplay/issues
Project-URL: Documentation, https://github.com/nsarang/framedisplay#readme
Keywords: dataframe display pandas jupyter notebook
Classifier: Development Status :: 5 - Production/Stable
Classifier: Intended Audience :: Developers
Classifier: License :: OSI Approved :: MIT License
Classifier: Programming Language :: Python :: 3
Classifier: Programming Language :: Python :: 3.9
Classifier: Programming Language :: Python :: 3.10
Classifier: Programming Language :: Python :: 3.11
Classifier: Programming Language :: Python :: 3.12
Classifier: Programming Language :: Python :: 3.13
Classifier: Topic :: Software Development :: Libraries :: Python Modules
Classifier: Topic :: Scientific/Engineering :: Information Analysis
Classifier: Topic :: Text Processing :: Markup :: HTML
Requires-Python: >=3.7
License-File: LICENSE
Requires-Dist: pandas<3
Requires-Dist: ipython
Dynamic: author
Dynamic: author-email
Dynamic: classifier
Dynamic: description
Dynamic: description-content-type
Dynamic: home-page
Dynamic: keywords
Dynamic: license-file
Dynamic: project-url
Dynamic: requires-dist
Dynamic: requires-python
Dynamic: summary
